indico_vc_zoom/__init__.py
indico_vc_zoom/blueprint.py
indico_vc_zoom/cli.py
indico_vc_zoom/controllers.py
indico_vc_zoom/fixtures.py
indico_vc_zoom/forms.py
indico_vc_zoom/notifications.py
indico_vc_zoom/plugin.py
indico_vc_zoom/task.py
indico_vc_zoom/util.py
indico_vc_zoom/api/__init__.py
indico_vc_zoom/api/client.py
indico_vc_zoom/static/dist/manifest.json
indico_vc_zoom/static/dist/css/main.d5d0f591.css
indico_vc_zoom/static/dist/css/main.d5d0f591.css.map
indico_vc_zoom/static/dist/js/main.bed851d6.bundle.js
indico_vc_zoom/static/dist/js/main.bed851d6.bundle.js.map
indico_vc_zoom/static/dist/js/monaco.css.worker.js
indico_vc_zoom/static/dist/js/monaco.css.worker.js.map
indico_vc_zoom/static/dist/js/monaco.editor.worker.js
indico_vc_zoom/static/dist/js/monaco.editor.worker.js.map
indico_vc_zoom/static/dist/js/monaco.html.worker.js
indico_vc_zoom/static/dist/js/monaco.html.worker.js.map
indico_vc_zoom/static/images/zoom_icon.svg
indico_vc_zoom/static/images/zoom_logo.svg
indico_vc_zoom/templates/buttons.html
indico_vc_zoom/templates/event_buttons.html
indico_vc_zoom/templates/extra_delete_msg.html
indico_vc_zoom/templates/info_box.html
indico_vc_zoom/templates/manage_event_info_box.html
indico_vc_zoom/templates/management_buttons.html
indico_vc_zoom/templates/room_labels.html
indico_vc_zoom/templates/vc_room_timetable_buttons.html
indico_vc_zoom/templates/emails/created.html
indico_vc_zoom/templates/emails/notify_start_url.html
indico_vc_zoom/templates/emails/remote_deleted.html
indico_vc_zoom/translations/messages-react.pot
indico_vc_zoom/translations/messages.pot
indico_vc_zoom/translations/cs_CZ/LC_MESSAGES/messages-js.po
indico_vc_zoom/translations/cs_CZ/LC_MESSAGES/messages-react.json
indico_vc_zoom/translations/cs_CZ/LC_MESSAGES/messages-react.po
indico_vc_zoom/translations/cs_CZ/LC_MESSAGES/messages.mo
indico_vc_zoom/translations/cs_CZ/LC_MESSAGES/messages.po
indico_vc_zoom/translations/de_DE/LC_MESSAGES/messages-js.po
indico_plugin_vc_zoom-3.3.4.dist-info/METADATA
indico_plugin_vc_zoom-3.3.4.dist-info/WHEEL
indico_plugin_vc_zoom-3.3.4.dist-info/entry_points.txt
indico_plugin_vc_zoom-3.3.4.dist-info/RECORD
