Metadata-Version: 2.4
Name: indico-plugin-vc-zoom
Version: 3.3.4
Summary: Zoom video-conferencing plugin for Indico
Project-URL: GitHub, https://github.com/indico/indico-plugins
Author: Giovanni Mariano (ENEA)
Author-email: Indico Team <indico-team@cern.ch>
License-Expression: MIT
Classifier: Environment :: Plugins
Classifier: Environment :: Web Environment
Classifier: License :: OSI Approved :: MIT License
Classifier: Programming Language :: Python :: 3.12
Requires-Python: <3.13,>=3.12.2
Requires-Dist: indico>=3.3.7.dev0
